Metadata-Version: 1.0
Name: rinobot-plugin
Version: 0.0.2
Summary: Rinobot plugin helpers
Home-page: https://github.com/rinocloud/rinobot-plugin
Author: Eoin Murray
Author-email: eoin@rinocloud.com
License: UNKNOWN
Keywords: rinocloud,rinobot,plugin
Platform: UNKNOWN
